MedLytics/__init__.py
MedLytics/text_analysis.py
medlytics-0.1.0.dist-info/LICENSE
medlytics-0.1.0.dist-info/METADATA
medlytics-0.1.0.dist-info/WHEEL
medlytics-0.1.0.dist-info/top_level.txt
medlytics-0.1.0.dist-info/RECORD
